{
	"$schema": "http://schema.management.azure.com/schemas/2015-01-01/deploymentTemplate.json#",
	"contentVersion": "1.0.0.0",
	"parameters": {
		"factoryName": {
			"type": "string",
			"metadata": "Data Factory name",
			"defaultValue": "demosdbx-jocj-df"
		},
		"AzureKeyVault1_properties_typeProperties_baseUrl": {
			"type": "string",
			"defaultValue": "https://demosdbx-jocj-vault.vault.azure.net/"
		}
	},
	"variables": {
		"factoryId": "[concat('Microsoft.DataFactory/factories/', parameters('factoryName'))]"
	},
	"resources": [
		{
			"name": "[concat(parameters('factoryName'), '/AzureKeyVault1')]",
			"type": "Microsoft.DataFactory/factories/linkedServices",
			"apiVersion": "2018-06-01",
			"properties": {
				"description": "Added Description",
				"annotations": [],
				"type": "AzureKeyVault",
				"typeProperties": {
					"baseUrl": "[parameters('AzureKeyVault1_properties_typeProperties_baseUrl')]"
				}
			},
			"dependsOn": []
		},
		{
			"name": "[concat(parameters('factoryName'), '/AzureDatabricks1')]",
			"type": "Microsoft.DataFactory/factories/linkedServices",
			"apiVersion": "2018-06-01",
			"properties": {
				"annotations": [],
				"type": "AzureDatabricks",
				"typeProperties": {
					"domain": "https://adb-3721847368411134.14.azuredatabricks.net",
					"accessToken": {
						"type": "AzureKeyVaultSecret",
						"store": {
							"referenceName": "AzureKeyVault1",
							"type": "LinkedServiceReference"
						},
						"secretName": "databricks-access-key"
					},
					"newClusterNodeType": "Standard_DS3_v2",
					"newClusterNumOfWorker": "1",
					"newClusterVersion": "7.0.x-scala2.12"
				}
			},
			"dependsOn": [
				"[concat(variables('factoryId'), '/linkedServices/AzureKeyVault1')]"
			]
		},
		{
			"name": "[concat(parameters('factoryName'), '/pipeline1')]",
			"type": "Microsoft.DataFactory/factories/pipelines",
			"apiVersion": "2018-06-01",
			"properties": {
				"activities": [
					{
						"name": "Notebook1",
						"type": "DatabricksNotebook",
						"dependsOn": [],
						"policy": {
							"timeout": "7.00:00:00",
							"retry": 0,
							"retryIntervalInSeconds": 30,
							"secureOutput": false,
							"secureInput": false
						},
						"userProperties": [],
						"typeProperties": {
							"notebookPath": "/adftutorial/mynotebook",
							"baseParameters": {
								"name": {
									"value": "@pipeline().parameters.name",
									"type": "Expression"
								}
							}
						},
						"linkedServiceName": {
							"referenceName": "AzureDatabricks1",
							"type": "LinkedServiceReference"
						}
					}
				],
				"parameters": {
					"name": {
						"type": "string"
					}
				},
				"annotations": []
			},
			"dependsOn": [
				"[concat(variables('factoryId'), '/linkedServices/AzureDatabricks1')]"
			]
		}
	]
}